rtl/memory/sram_1rw.v
`timescale 1ns/1ps

// ============================================================================
// Project      : SNN_ECG_V2
// Module       : sram_1rw
// Description  : Behavioral model for a synchronous single-port (1RW) SRAM.
//                - FPGA: Infers block RAM (BRAM).
//                - ASIC: Intended to be replaced by a foundry SRAM macro.
//                - Read latency: 1 clock cycle.
// ============================================================================

module sram_1rw #(
    parameter DATA_WIDTH = 16,
    parameter ADDR_WIDTH = 10,
    parameter INIT_FILE  = "" // Path to initialization memory file
)(
    input  wire                   clk,
    input  wire                   ce,
    input  wire                   we,
    input  wire [ADDR_WIDTH-1:0]  addr,
    input  wire [DATA_WIDTH-1:0]  wdata,
    output reg  [DATA_WIDTH-1:0]  rdata
);

    // BRAM inference attribute for Vivado synthesis
    (* ram_style = "block" *)
    reg [DATA_WIDTH-1:0] mem [0:(1 << ADDR_WIDTH) - 1];

    // Synchronous read/write logic
    always @(posedge clk) begin
        if (ce) begin
            if (we) begin
                mem[addr] <= wdata;
            end else begin
                rdata <= mem[addr];
            end
        end
    end

    // ========================================================================
    // Simulation Initialization
    // ========================================================================
    // synthesis translate_off
    integer idx;
    initial begin
        // Initialize memory to zero
        for (idx = 0; idx < (1 << ADDR_WIDTH); idx = idx + 1) begin
            mem[idx] = {DATA_WIDTH{1'b0}};
        end
        
        // Load initial values if file provided
        if (INIT_FILE != "") begin
            $readmemh(INIT_FILE, mem);
        end
    end
    // synthesis translate_on

endmodule

rtl/memory/weight_decode.v
`timescale 1ns/1ps

// ============================================================================
// Project      : SNN_ECG_V2
// Module       : weight_decode
// Description  : Synaptic weight retrieval engine. Performs a two-stage 
//                indirect SRAM lookup to stream weight/destination pairs.
//                1. Weight_Entrance (WE): Maps Neuron ID to {base_ptr, count}
//                2. Weight_Connection (WC): Stores sequences of {weight, dst_id}
// ============================================================================

module weight_decode #(
    parameter W_WIDTH   = 6,
    parameter ID_WIDTH  = 10,
    parameter WE_AWIDTH = 10,
    parameter WC_AWIDTH = 15
)(
    input  wire                 clk,
    input  wire                 rst_n,
    
    // Request Interface
    input  wire [ID_WIDTH-1:0]  req_neuron_id,
    input  wire                 req_valid,
    
    // Stream Output Interface
    output reg  [W_WIDTH-1:0]   out_weight,
    output reg  [ID_WIDTH-1:0]  out_dst_id,
    output reg                  out_valid,
    output reg                  out_last,
    output wire                 ready
);

    // ========================================================================
    // Internal Constants
    // ========================================================================
    localparam WE_DWIDTH = WC_AWIDTH + ID_WIDTH; // 25 bits
    localparam WC_DWIDTH = W_WIDTH  + ID_WIDTH;  // 16 bits

    // ========================================================================
    // SRAM Instances
    // ========================================================================
    reg  [WE_AWIDTH-1:0] we_addr;
    reg                  we_ce, we_we;
    wire [WE_DWIDTH-1:0] we_rdata;

    sram_1rw #(
        .DATA_WIDTH (WE_DWIDTH),
        .ADDR_WIDTH (WE_AWIDTH),
        .INIT_FILE  ("Weight_Entrance.mem")
    ) u_went (
        .clk(clk), .ce(we_ce), .we(we_we),
        .addr(we_addr), .wdata({WE_DWIDTH{1'b0}}), .rdata(we_rdata)
    );

    reg  [WC_AWIDTH-1:0] wc_addr;
    reg                  wc_ce, wc_we;
    wire [WC_DWIDTH-1:0] wc_rdata;

    sram_1rw #(
        .DATA_WIDTH (WC_DWIDTH),
        .ADDR_WIDTH (WC_AWIDTH),
        .INIT_FILE  ("Weight_Connection.mem")
    ) u_wcon (
        .clk(clk), .ce(wc_ce), .we(wc_we),
        .addr(wc_addr), .wdata({WC_DWIDTH{1'b0}}), .rdata(wc_rdata)
    );

    // ========================================================================
    // FSM States
    // ========================================================================
    localparam ST_IDLE       = 3'd0;
    localparam ST_WAIT_ENT   = 3'd1;
    localparam ST_LATCH_ENT  = 3'd2;
    localparam ST_WAIT_CONN  = 3'd3;
    localparam ST_OUT_CONN   = 3'd4;

    reg [2:0]           state;
    reg [WC_AWIDTH-1:0] connection_addr;
    reg [ID_WIDTH-1:0]  remaining_connections;

    assign ready = (state == ST_IDLE);

    always @(posedge clk or negedge rst_n) begin
        if (!rst_n) begin
            state                 <= ST_IDLE;
            out_valid             <= 1'b0;
            out_last              <= 1'b0;
            out_weight            <= {W_WIDTH{1'b0}};
            out_dst_id            <= {ID_WIDTH{1'b0}};
            connection_addr       <= {WC_AWIDTH{1'b0}};
            remaining_connections <= {ID_WIDTH{1'b0}};
            we_ce <= 1'b0; we_we <= 1'b0; we_addr <= {WE_AWIDTH{1'b0}};
            wc_ce <= 1'b0; wc_we <= 1'b0; wc_addr <= {WC_AWIDTH{1'b0}};
        end else begin
           out_valid <= 1'b0;
	   out_last  <= 1'b0;
           we_ce     <= 1'b0;
           we_we     <= 1'b0;
           wc_ce     <= 1'b0;
           wc_we     <= 1'b0;

            case (state)
                ST_IDLE: begin
                    if (req_valid) begin
                        we_ce   <= 1'b1;
                        we_we   <= 1'b0;
                        we_addr <= req_neuron_id[WE_AWIDTH-1:0];
                        state   <= ST_WAIT_ENT;
                    end
                end

                ST_WAIT_ENT: begin
                    // Wait one clock cycle for synchronous SRAM read
                    state <= ST_LATCH_ENT;
                end

                ST_LATCH_ENT: begin
                    connection_addr       <= we_rdata[WE_DWIDTH-1:ID_WIDTH];
                    remaining_connections <= we_rdata[ID_WIDTH-1:0];

                    if (we_rdata[ID_WIDTH-1:0] == 0) begin
                        state <= ST_IDLE;
                    end else begin
                        wc_ce   <= 1'b1;
                        wc_we   <= 1'b0;
                        wc_addr <= we_rdata[WE_DWIDTH-1:ID_WIDTH];
                        state   <= ST_WAIT_CONN;
                    end
                end

                ST_WAIT_CONN: begin
                    // Wait one clock cycle for synchronous SRAM read
                    state <= ST_OUT_CONN;
                end

                ST_OUT_CONN: begin
                    // One weight/destination pair is streamed each clock cycle
                    // until all connections have been processed.
                    out_weight <= wc_rdata[WC_DWIDTH-1:ID_WIDTH];
                    out_dst_id <= wc_rdata[ID_WIDTH-1:0];
                    out_valid  <= 1'b1;

                    if (remaining_connections == 1) begin
                        out_last <= 1'b1;
                        state    <= ST_IDLE;
                    end else begin
                        remaining_connections <= remaining_connections - 1;
                        connection_addr       <= connection_addr + 1;
                        wc_ce                 <= 1'b1;
                        wc_we                 <= 1'b0;
                        wc_addr               <= connection_addr + 1;
                        state                 <= ST_WAIT_CONN;
                    end
                end

                default: begin
    state <= ST_IDLE;
    out_valid <= 1'b0;
    out_last  <= 1'b0;
end
            endcase
        end
    end

endmodule

tb/tb_weight_decode.v
`timescale 1ns/1ps

// ============================================================================
// Testbench    : tb_weight_decode
// Description  : Complete self-checking testbench for the weight_decode FSM.
//                Assumes memory files are pre-loaded via Vivado sources.
//                Verifies FSM states, streaming outputs, edge cases, and 
//                includes strict timeout mechanisms to prevent hangs.
// ============================================================================

module tb_weight_decode;

    // ------------------------------------------------------------------------
    // Parameters & Timing
    // ------------------------------------------------------------------------
    parameter CLK_PERIOD = 10;
    parameter W_WIDTH    = 6;
    parameter ID_WIDTH   = 10;
    parameter WE_AWIDTH  = 10;
    parameter WC_AWIDTH  = 15;
    parameter TIMEOUT    = 50; // Max cycles to wait for events

    // ------------------------------------------------------------------------
    // DUT Signals
    // ------------------------------------------------------------------------
    reg                 clk;
    reg                 rst_n;
    
    reg  [ID_WIDTH-1:0] req_neuron_id;
    reg                 req_valid;
    
    wire [W_WIDTH-1:0]  out_weight;
    wire [ID_WIDTH-1:0] out_dst_id;
    wire                out_valid;
    wire                out_last;
    wire                ready;

    // ------------------------------------------------------------------------
    // Testbench Variables
    // ------------------------------------------------------------------------
    integer pass_count;
    integer fail_count;
    integer initial_fail_count;
    integer wait_cnt;
    integer i;
    reg [255:0] current_test;

    // ------------------------------------------------------------------------
    // DUT Instantiation
    // ------------------------------------------------------------------------
    weight_decode #(
        .W_WIDTH   (W_WIDTH),
        .ID_WIDTH  (ID_WIDTH),
        .WE_AWIDTH (WE_AWIDTH),
        .WC_AWIDTH (WC_AWIDTH)
    ) dut (
        .clk           (clk),
        .rst_n         (rst_n),
        .req_neuron_id (req_neuron_id),
        .req_valid     (req_valid),
        .out_weight    (out_weight),
        .out_dst_id    (out_dst_id),
        .out_valid     (out_valid),
        .out_last      (out_last),
        .ready         (ready)
    );

    // ------------------------------------------------------------------------
    // Clock Generation
    // ------------------------------------------------------------------------
    initial begin
        clk = 1'b0;
        forever #(CLK_PERIOD / 2) clk = ~clk;
    end

    // ------------------------------------------------------------------------
    // VCD Dump
    // ------------------------------------------------------------------------
    initial begin
        $dumpfile("weight_decode.vcd");
        $dumpvars(0, tb_weight_decode);
    end

    // ------------------------------------------------------------------------
    // Checking Logic Tasks
    // ------------------------------------------------------------------------
    task verify_output;
        input [W_WIDTH-1:0]  exp_weight;
        input [ID_WIDTH-1:0] exp_dst_id;
        input                exp_last;
        begin
            if ((out_weight !== exp_weight) || (out_dst_id !== exp_dst_id) || (out_last !== exp_last)) begin
                $display("[%0t] [FAIL] %s | Exp: W=%0d ID=%0d L=%0b | Got: W=%0d ID=%0d L=%0b", 
                         $time, current_test, exp_weight, exp_dst_id, exp_last, out_weight, out_dst_id, out_last);
                fail_count = fail_count + 1;
            end else begin
                $display("[%0t] [PASS] %s", $time, current_test);
                pass_count = pass_count + 1;
            end
        end
    endtask

    task wait_for_valid;
        begin
            wait_cnt = 0;
            while (!out_valid && wait_cnt < TIMEOUT) begin
                @(negedge clk);
                wait_cnt = wait_cnt + 1;
            end
            if (wait_cnt >= TIMEOUT) begin
                $display("[%0t] [FAIL] %s | TIMEOUT: out_valid did not assert within %0d cycles.", $time, current_test, TIMEOUT);
                fail_count = fail_count + 1;
            end
        end
    endtask

    task wait_for_ready;
        begin
            wait_cnt = 0;
            while (!ready && wait_cnt < TIMEOUT) begin
                // If out_valid asserts unexpectedly while waiting for ready
                if (out_valid) begin
                    $display("[%0t] [FAIL] %s | out_valid asserted unexpectedly while waiting for ready!", $time, current_test);
                    fail_count = fail_count + 1;
                end
                @(negedge clk);
                wait_cnt = wait_cnt + 1;
            end
            
            if (wait_cnt >= TIMEOUT) begin
                $display("[%0t] [FAIL] %s | TIMEOUT: FSM did not return to ready within %0d cycles.", $time, current_test, TIMEOUT);
                fail_count = fail_count + 1;
            end else begin
                $display("[%0t] [PASS] %s", $time, current_test);
                pass_count = pass_count + 1;
            end
        end
    endtask

    // ------------------------------------------------------------------------
    // Main Verification Sequence
    // ------------------------------------------------------------------------
    initial begin
        pass_count = 0;
        fail_count = 0;
        
        req_neuron_id = 0;
        req_valid     = 0;
        
        // Assert Reset
        rst_n = 1'b0;
        #(CLK_PERIOD * 2);
        rst_n = 1'b1;

        $display("=================================================");
        $display(" Starting Verification: weight_decode");
        $display("=================================================");

        // --------------------------------------------------------------------
        // TEST 0: Reset State Verification
        // --------------------------------------------------------------------
        current_test = "Verify ready == 1 immediately after reset";
        if (ready !== 1'b1) begin
            $display("[%0t] [FAIL] %s | Expected ready=1, Got ready=0", $time, current_test);
            fail_count = fail_count + 1;
        end else begin
            $display("[%0t] [PASS] %s", $time, current_test);
            pass_count = pass_count + 1;
        end

        // --------------------------------------------------------------------
        // TEST 1: Zero Connections (Early Exit Check)
        // --------------------------------------------------------------------
        current_test = "Neuron 0 (0 connections) - FSM should return to IDLE without out_valid";
        @(negedge clk);
        req_neuron_id = 10'd0;
        req_valid     = 1'b1;
        @(negedge clk);
        req_valid     = 1'b0;
        
        // Wait for FSM to process and return to IDLE (also checks for unexpected out_valid)
        wait_for_ready();

        // --------------------------------------------------------------------
        // TEST 2: Single Connection & Ready=0 Check & Pulse Width Check
        // --------------------------------------------------------------------
        current_test = "Neuron 1 (1 connection) - Checking output & out_last";
        @(negedge clk);
        req_neuron_id = 10'd1;
        req_valid     = 1'b1;
        @(negedge clk);
        req_valid     = 1'b0;

        current_test = "Verify ready == 0 while FSM is busy";
        if (ready !== 1'b0) begin
            $display("[%0t] [FAIL] %s | Expected ready=0, Got ready=1", $time, current_test);
            fail_count = fail_count + 1;
        end else begin
            $display("[%0t] [PASS] %s", $time, current_test);
            pass_count = pass_count + 1;
        end

        current_test = "Neuron 1 (1 connection) - Data Validation";
        wait_for_valid();
        verify_output(6'd11, 10'd111, 1'b1); // Exp: Weight 11, Dest 111, Last 1
        
        // Check that out_valid is strictly a 1-cycle pulse
        current_test = "Verify out_valid is a one-clock-cycle pulse";
        @(negedge clk);
        if (out_valid !== 1'b0) begin
            $display("[%0t] [FAIL] %s | out_valid remained high for multiple cycles!", $time, current_test);
            fail_count = fail_count + 1;
        end else begin
            $display("[%0t] [PASS] %s", $time, current_test);
            pass_count = pass_count + 1;
        end
        
        // Wait for FSM to return to IDLE safely
        current_test = "FSM returned to IDLE after 1-connection stream";
        wait_for_ready();

        // --------------------------------------------------------------------
        // TEST 3: Multiple Connections & Busy-Request Ignore Strengthening
        // --------------------------------------------------------------------
        current_test = "Neuron 2 (3 connections) - Checking output 1";
        @(negedge clk);
        req_neuron_id = 10'd2;
        req_valid     = 1'b1;
        @(negedge clk);
        req_valid     = 1'b0;

        // Inject an invalid request while FSM is busy
        @(negedge clk);
        req_neuron_id = 10'd99;
        req_valid     = 1'b1;
        @(negedge clk);
        req_valid     = 1'b0; 

        // Check Connection 1
        wait_for_valid();
        verify_output(6'd21, 10'd201, 1'b0); // Last = 0

        // Check Connection 2
        current_test = "Neuron 2 (3 connections) - Checking output 2";
        @(negedge clk); // Step past current valid
        wait_for_valid();
        verify_output(6'd22, 10'd202, 1'b0); // Last = 0

        // Check Connection 3
        current_test = "Neuron 2 (3 connections) - Checking output 3 (Last)";
        @(negedge clk); // Step past current valid
        wait_for_valid();
        verify_output(6'd23, 10'd203, 1'b1); // Last = 1

        // --------------------------------------------------------------------
        // TEST 4: Prove ignored request yields no extra outputs
        // --------------------------------------------------------------------
        current_test = "Verify request issued while busy was ignored (no ghost streams)";
        initial_fail_count = fail_count; 
        
        @(negedge clk); // Step past the last valid cycle
        for (i = 0; i < 20; i = i + 1) begin
            if (out_valid) begin
                $display("[%0t] [FAIL] %s | Unexpected out_valid detected!", $time, current_test);
                fail_count = fail_count + 1;
            end
            @(negedge clk);
        end
        
        // If fail_count hasn't increased, the loop passed cleanly
        if (fail_count == initial_fail_count) begin
            $display("[%0t] [PASS] %s", $time, current_test);
            pass_count = pass_count + 1;
        end

        // Verify FSM returned to IDLE safely
        current_test = "FSM returned to IDLE after multi-connection stream";
        wait_for_ready();

        // --------------------------------------------------------------------
        // Simulation Summary
        // --------------------------------------------------------------------
        $display("=================================================");
        if (fail_count == 0) begin
            $display(" [SUCCESS] All %0d checks PASSED!", pass_count);
        end else begin
            $display(" [FAILED] %0d out of %0d checks FAILED.", fail_count, (pass_count + fail_count));
        end
        $display("=================================================");
        
        #20 $finish;
    end

endmodule

sim/test_neuron_state_sram/test_neuron_state_sram.sim/sim_1/behav/xsim/weight_decode.vcd
$date
   Thu Jul  2 14:14:09 2026
$end

$version
  2024.2.0
  $dumpfile ("weight_decode.vcd") 
$end

$timescale
  1ps
$end

$scope module tb_weight_decode $end
$var reg 1 ! clk $end
$var reg 1 " rst_n $end
$var reg 10 # req_neuron_id [9:0] $end
$var reg 1 $ req_valid $end
$var wire 6 % out_weight [5:0] $end
$var wire 10 & out_dst_id [9:0] $end
$var wire 1 ' out_valid $end
$var wire 1 ( out_last $end
$var wire 1 ) ready $end
$var integer 32 * pass_count [31:0] $end
$var integer 32 + fail_count [31:0] $end
$var integer 32 , initial_fail_count [31:0] $end
$var integer 32 - wait_cnt [31:0] $end
$var integer 32 . i [31:0] $end
$var reg 256 / current_test [255:0] $end
$scope module dut $end
$var wire 1 0 clk $end
$var wire 1 1 rst_n $end
$var wire 10 2 req_neuron_id [9:0] $end
$var wire 1 3 req_valid $end
$var reg 6 4 out_weight [5:0] $end
$var reg 10 5 out_dst_id [9:0] $end
$var reg 1 6 out_valid $end
$var reg 1 7 out_last $end
$var wire 1 ) ready $end
$var reg 10 8 we_addr [9:0] $end
$var reg 1 9 we_ce $end
$var reg 1 : we_we $end
$var wire 25 ; we_rdata [24:0] $end
$var reg 15 < wc_addr [14:0] $end
$var reg 1 = wc_ce $end
$var reg 1 > wc_we $end
$var wire 16 ? wc_rdata [15:0] $end
$var reg 3 @ state [2:0] $end
$var reg 15 A connection_addr [14:0] $end
$var reg 10 B remaining_connections [9:0] $end
$scope module u_went $end
$var wire 1 0 clk $end
$var wire 1 C ce $end
$var wire 1 D we $end
$var wire 10 E addr [9:0] $end
$var wire 25 F wdata [24:0] $end
$var reg 25 G rdata [24:0] $end
$var integer 32 H idx [31:0] $end
$upscope $end
$scope module u_wcon $end
$var wire 1 0 clk $end
$var wire 1 I ce $end
$var wire 1 J we $end
$var wire 15 K addr [14:0] $end
$var wire 16 L wdata [15:0] $end
$var reg 16 M rdata [15:0] $end
$var integer 32 N idx [31:0] $end
$upscope $end
$upscope $end
$scope task verify_output $end
$var reg 6 O exp_weight [5:0] $end
$var reg 10 P exp_dst_id [9:0] $end
$var reg 1 Q exp_last $end
$upscope $end
$scope task wait_for_valid $end
$upscope $end
$scope task wait_for_ready $end
$upscope $end
$upscope $end
$enddefinitions $end

#0
$dumpvars
0!
0"
b0 #
0$
b0 %
b0 &
0'
0(
1)
b0 *
b0 +
bx ,
bx -
bx .
bx /
00
01
b0 2
03
b0 4
b0 5
06
07
b0 8
09
0:
bx ;
b0 <
0=
0>
bx ?
b0 @
b0 A
b0 B
0C
0D
b0 E
b0 F
bx G
b10000000000 H
0I
0J
b0 K
b0 L
bx M
b1000000000000000 N
bx O
bx P
xQ
$end

#5000
1!
10

#10000
0!
00

#15000
1!
10

#20000
0!
1"
1$
b1 *
b111001001100101011101000111010101110010011011100010000001110100011011110010000001001001010001000100110001000101001000000111011101101001011101000110100001101111011101010111010000100000011011110111010101110100010111110111011001100001011011000110100101100100 /
00
11
13

#25000
1!
0)
10
19
b1 @
1C

#30000
0!
0$
b0 -
00
03

#35000
1!
10
09
b0 ;
b10 @
0C
b0 G

#40000
0!
b1 -
00

#45000
1!
1)
10
b0 @

#50000
0!
b10 *
b10 -
b110111101101110001010010010000000101101001000000100001101101000011001010110001101101011011010010110111001100111001000000110111101110101011101000111000001110101011101000010000000100110001000000110111101110101011101000101111101101100011000010111001101110100 /
00

#55000
1!
10

#60000
0!
b1 #
1$
00
b1 2
13

#65000
1!
0)
10
b1 8
19
b1 @
1C
b1 E

#70000
0!
0$
b11 *
b0 -
b10100000110001001000000110001101101111011011100110111001100101011000110111010001101001011011110110111000101001001000000010110100100000010001000110000101110100011000010010000001010110011000010110110001101001011001000110000101110100011010010110111101101110 /
00
03

#75000
1!
10
09
b10 @
0C

#80000
0!
b1 -
00

#85000
1!
1)
10
b0 @

#90000
0!
b10 -
00

#95000
1!
10

#100000
0!
b11 -
00

#105000
1!
10

#110000
0!
b100 -
00

#115000
1!
10

#120000
0!
b101 -
00

#125000
1!
10

#130000
0!
b110 -
00

#135000
1!
10

#140000
0!
b111 -
00

#145000
1!
10

#150000
0!
b1000 -
00

#155000
1!
10

#160000
0!
b1001 -
00

#165000
1!
10

#170000
0!
b1010 -
00

#175000
1!
10

#180000
0!
b1011 -
00

#185000
1!
10

#190000
0!
b1100 -
00

#195000
1!
10

#200000
0!
b1101 -
00

#205000
1!
10

#210000
0!
b1110 -
00

#215000
1!
10

#220000
0!
b1111 -
00

#225000
1!
10

#230000
0!
b10000 -
00

#235000
1!
10

#240000
0!
b10001 -
00

#245000
1!
10

#250000
0!
b10010 -
00

#255000
1!
10

#260000
0!
b10011 -
00

#265000
1!
10

#270000
0!
b10100 -
00

#275000
1!
10

#280000
0!
b10101 -
00

#285000
1!
10

#290000
0!
b10110 -
00

#295000
1!
10

#300000
0!
b10111 -
00

#305000
1!
10

#310000
0!
b11000 -
00

#315000
1!
10

#320000
0!
b11001 -
00

#325000
1!
10

#330000
0!
b11010 -
00

#335000
1!
10

#340000
0!
b11011 -
00

#345000
1!
10

#350000
0!
b11100 -
00

#355000
1!
10

#360000
0!
b11101 -
00

#365000
1!
10

#370000
0!
b11110 -
00

#375000
1!
10

#380000
0!
b11111 -
00

#385000
1!
10

#390000
0!
b100000 -
00

#395000
1!
10

#400000
0!
b100001 -
00

#405000
1!
10

#410000
0!
b100010 -
00

#415000
1!
10

#420000
0!
b100011 -
00

#425000
1!
10

#430000
0!
b100100 -
00

#435000
1!
10

#440000
0!
b100101 -
00

#445000
1!
10

#450000
0!
b100110 -
00

#455000
1!
10

#460000
0!
b100111 -
00

#465000
1!
10

#470000
0!
b101000 -
00

#475000
1!
10

#480000
0!
b101001 -
00

#485000
1!
10

#490000
0!
b101010 -
00

#495000
1!
10

#500000
0!
b101011 -
00

#505000
1!
10

#510000
0!
b101100 -
00

#515000
1!
10

#520000
0!
b101101 -
00

#525000
1!
10

#530000
0!
b101110 -
00

#535000
1!
10

#540000
0!
b101111 -
00

#545000
1!
10

#550000
0!
b110000 -
00

#555000
1!
10

#560000
0!
b110001 -
00

#565000
1!
10

#570000
0!
b10 +
b110010 -
b111011001100001011011000110100101100100001000000110100101110011001000000110000100100000011011110110111001100101001011010110001101101100011011110110001101101011001011010110001101111001011000110110110001100101001000000111000001110101011011000111001101100101 /
00
b1011 O
b1101111 P
1Q

#575000
1!
10

#580000
0!
b101 *
b0 -
b110001101101111011011100110111001100101011000110111010001101001011011110110111001110011001010010010000000101101001000000100001101101000011001010110001101101011011010010110111001100111001000000110111101110101011101000111000001110101011101000010000000110001 /
00

#585000
1!
10

#590000
0!
b10 #
1$
00
b10 2
13

#595000
1!
0)
10
b10 8
19
b1 @
1C
b10 E

#600000
0!
0$
00
03

#605000
1!
10
09
b10 @
0C

#610000
0!
b1100011 #
1$
00
b1100011 2
13

#615000
1!
1)
10
b0 @

#620000
0!
0$
00
03

#625000
1!
10

#630000
0!
b1 -
00

#635000
1!
10

#640000
0!
b10 -
00

#645000
1!
10

#650000
0!
b11 -
00

#655000
1!
10

#660000
0!
b100 -
00

#665000
1!
10

#670000
0!
b101 -
00

#675000
1!
10

#680000
0!
b110 -
00

#685000
1!
10

#690000
0!
b111 -
00

#695000
1!
10

#700000
0!
b1000 -
00

#705000
1!
10

#710000
0!
b1001 -
00

#715000
1!
10

#720000
0!
b1010 -
00

#725000
1!
10

#730000
0!
b1011 -
00

#735000
1!
10

#740000
0!
b1100 -
00

#745000
1!
10

#750000
0!
b1101 -
00

#755000
1!
10

#760000
0!
b1110 -
00

#765000
1!
10

#770000
0!
b1111 -
00

#775000
1!
10

#780000
0!
b10000 -
00

#785000
1!
10

#790000
0!
b10001 -
00

#795000
1!
10

#800000
0!
b10010 -
00

#805000
1!
10

#810000
0!
b10011 -
00

#815000
1!
10

#820000
0!
b10100 -
00

#825000
1!
10

#830000
0!
b10101 -
00

#835000
1!
10

#840000
0!
b10110 -
00

#845000
1!
10

#850000
0!
b10111 -
00

#855000
1!
10

#860000
0!
b11000 -
00

#865000
1!
10

#870000
0!
b11001 -
00

#875000
1!
10

#880000
0!
b11010 -
00

#885000
1!
10

#890000
0!
b11011 -
00

#895000
1!
10

#900000
0!
b11100 -
00

#905000
1!
10

#910000
0!
b11101 -
00

#915000
1!
10

#920000
0!
b11110 -
00

#925000
1!
10

#930000
0!
b11111 -
00

#935000
1!
10

#940000
0!
b100000 -
00

#945000
1!
10

#950000
0!
b100001 -
00

#955000
1!
10

#960000
0!
b100010 -
00

#965000
1!
10

#970000
0!
b100011 -
00

#975000
1!
10

#980000
0!
b100100 -
00

#985000
1!
10

#990000
0!
b100101 -
00

#995000
1!
10

#1000000
0!
b100110 -
00
