rtl/memory/sram_1rw.v
`timescale 1ns/1ps

// ============================================================================
// Project      : SNN_ECG_V2
// Module       : sram_1rw
// Description  : Behavioral model for a synchronous single-port (1RW) SRAM.
//                - FPGA: Infers block RAM (BRAM).
//                - ASIC: Intended to be replaced by a foundry SRAM macro.
//                - Read latency: 1 clock cycle.
// ============================================================================

module sram_1rw #(
    parameter DATA_WIDTH = 16,
    parameter ADDR_WIDTH = 10,
    parameter INIT_FILE  = "" // Path to initialization memory file
)(
    input  wire                   clk,
    input  wire                   ce,
    input  wire                   we,
    input  wire [ADDR_WIDTH-1:0]  addr,
    input  wire [DATA_WIDTH-1:0]  wdata,
    output reg  [DATA_WIDTH-1:0]  rdata
);

    // BRAM inference attribute for Vivado synthesis
    (* ram_style = "block" *)
    reg [DATA_WIDTH-1:0] mem [0:(1 << ADDR_WIDTH) - 1];

    // Synchronous read/write logic
    always @(posedge clk) begin
        if (ce) begin
            if (we) begin
                mem[addr] <= wdata;
            end else begin
                rdata <= mem[addr];
            end
        end
    end

    // ========================================================================
    // Simulation Initialization
    // ========================================================================
    // synthesis translate_off
    integer idx;
    initial begin
        // Initialize memory to zero
        for (idx = 0; idx < (1 << ADDR_WIDTH); idx = idx + 1) begin
            mem[idx] = {DATA_WIDTH{1'b0}};
        end
        
        // Load initial values if file provided
        if (INIT_FILE != "") begin
            $readmemh(INIT_FILE, mem);
        end
    end
    // synthesis translate_on

endmodule

rtl/memory/weight_decode.v
`timescale 1ns/1ps

// ============================================================================
// Project      : SNN_ECG_V2
// Module       : weight_decode
// Description  : Synaptic weight retrieval engine. Performs a two-stage 
//                indirect SRAM lookup to stream weight/destination pairs.
//                1. Weight_Entrance (WE): Maps Neuron ID to {base_ptr, count}
//                2. Weight_Connection (WC): Stores sequences of {weight, dst_id}
// ============================================================================

module weight_decode #(
    parameter W_WIDTH   = 6,
    parameter ID_WIDTH  = 10,
    parameter WE_AWIDTH = 10,
    parameter WC_AWIDTH = 15
)(
    input  wire                 clk,
    input  wire                 rst_n,
    
    // Request Interface
    input  wire [ID_WIDTH-1:0]  req_neuron_id,
    input  wire                 req_valid,
    
    // Stream Output Interface
    output reg  [W_WIDTH-1:0]   out_weight,
    output reg  [ID_WIDTH-1:0]  out_dst_id,
    output reg                  out_valid,
    output reg                  out_last,
    output wire                 ready
);

    // ========================================================================
    // Internal Constants
    // ========================================================================
    localparam WE_DWIDTH = WC_AWIDTH + ID_WIDTH; // 25 bits
    localparam WC_DWIDTH = W_WIDTH  + ID_WIDTH;  // 16 bits

    // ========================================================================
    // SRAM Instances
    // ========================================================================
    reg  [WE_AWIDTH-1:0] we_addr;
    reg                  we_ce, we_we;
    wire [WE_DWIDTH-1:0] we_rdata;

    sram_1rw #(
        .DATA_WIDTH (WE_DWIDTH),
        .ADDR_WIDTH (WE_AWIDTH),
        .INIT_FILE  ("Weight_Entrance.mem")
    ) u_went (
        .clk(clk), .ce(we_ce), .we(we_we),
        .addr(we_addr), .wdata({WE_DWIDTH{1'b0}}), .rdata(we_rdata)
    );

    reg  [WC_AWIDTH-1:0] wc_addr;
    reg                  wc_ce, wc_we;
    wire [WC_DWIDTH-1:0] wc_rdata;

    sram_1rw #(
        .DATA_WIDTH (WC_DWIDTH),
        .ADDR_WIDTH (WC_AWIDTH),
        .INIT_FILE  ("Weight_Connection.mem")
    ) u_wcon (
        .clk(clk), .ce(wc_ce), .we(wc_we),
        .addr(wc_addr), .wdata({WC_DWIDTH{1'b0}}), .rdata(wc_rdata)
    );

    // ========================================================================
    // FSM States
    // ========================================================================
    localparam ST_IDLE       = 3'd0;
    localparam ST_WAIT_ENT   = 3'd1;
    localparam ST_LATCH_ENT  = 3'd2;
    localparam ST_WAIT_CONN  = 3'd3;
    localparam ST_OUT_CONN   = 3'd4;

    reg [2:0]           state;
    reg [WC_AWIDTH-1:0] connection_addr;
    reg [ID_WIDTH-1:0]  remaining_connections;

    assign ready = (state == ST_IDLE);

    always @(posedge clk or negedge rst_n) begin
        if (!rst_n) begin
            state                 <= ST_IDLE;
            out_valid             <= 1'b0;
            out_last              <= 1'b0;
            out_weight            <= {W_WIDTH{1'b0}};
            out_dst_id            <= {ID_WIDTH{1'b0}};
            connection_addr       <= {WC_AWIDTH{1'b0}};
            remaining_connections <= {ID_WIDTH{1'b0}};
            we_ce <= 1'b0; we_we <= 1'b0; we_addr <= {WE_AWIDTH{1'b0}};
            wc_ce <= 1'b0; wc_we <= 1'b0; wc_addr <= {WC_AWIDTH{1'b0}};
        end else begin
           out_valid <= 1'b0;
	   out_last  <= 1'b0;
           we_ce     <= 1'b0;
           we_we     <= 1'b0;
           wc_ce     <= 1'b0;
           wc_we     <= 1'b0;

            case (state)
                ST_IDLE: begin
                    if (req_valid) begin
                        we_ce   <= 1'b1;
                        we_we   <= 1'b0;
                        we_addr <= req_neuron_id[WE_AWIDTH-1:0];
                        state   <= ST_WAIT_ENT;
                    end
                end

                ST_WAIT_ENT: begin
                    // Wait one clock cycle for synchronous SRAM read
                    state <= ST_LATCH_ENT;
                end

                ST_LATCH_ENT: begin
                    connection_addr       <= we_rdata[WE_DWIDTH-1:ID_WIDTH];
                    remaining_connections <= we_rdata[ID_WIDTH-1:0];

                    if (we_rdata[ID_WIDTH-1:0] == 0) begin
                        state <= ST_IDLE;
                    end else begin
                        wc_ce   <= 1'b1;
                        wc_we   <= 1'b0;
                        wc_addr <= we_rdata[WE_DWIDTH-1:ID_WIDTH];
                        state   <= ST_WAIT_CONN;
                    end
                end

                ST_WAIT_CONN: begin
                    // Wait one clock cycle for synchronous SRAM read
                    state <= ST_OUT_CONN;
                end

                ST_OUT_CONN: begin
                    // One weight/destination pair is streamed each clock cycle
                    // until all connections have been processed.
                    out_weight <= wc_rdata[WC_DWIDTH-1:ID_WIDTH];
                    out_dst_id <= wc_rdata[ID_WIDTH-1:0];
                    out_valid  <= 1'b1;

                    if (remaining_connections == 1) begin
                        out_last <= 1'b1;
                        state    <= ST_IDLE;
                    end else begin
                        remaining_connections <= remaining_connections - 1;
                        connection_addr       <= connection_addr + 1;
                        wc_ce                 <= 1'b1;
                        wc_we                 <= 1'b0;
                        wc_addr               <= connection_addr + 1;
                        state                 <= ST_WAIT_CONN;
                    end
                end

                default: begin
    state <= ST_IDLE;
    out_valid <= 1'b0;
    out_last  <= 1'b0;
end
            endcase
        end
    end

endmodule

tb/tb_weight_decode.v
`timescale 1ns/1ps

// ============================================================================
// Testbench    : tb_weight_decode
// Description  : Complete self-checking testbench for the weight_decode FSM.
//                Assumes memory files are pre-loaded via Vivado sources.
//                Verifies FSM states, streaming outputs, edge cases, and 
//                includes strict timeout mechanisms to prevent hangs.
// ============================================================================

module tb_weight_decode;

    // ------------------------------------------------------------------------
    // Parameters & Timing
    // ------------------------------------------------------------------------
    parameter CLK_PERIOD = 10;
    parameter W_WIDTH    = 6;
    parameter ID_WIDTH   = 10;
    parameter WE_AWIDTH  = 10;
    parameter WC_AWIDTH  = 15;
    parameter TIMEOUT    = 50; // Max cycles to wait for events

    // ------------------------------------------------------------------------
    // DUT Signals
    // ------------------------------------------------------------------------
    reg                 clk;
    reg                 rst_n;
    
    reg  [ID_WIDTH-1:0] req_neuron_id;
    reg                 req_valid;
    
    wire [W_WIDTH-1:0]  out_weight;
    wire [ID_WIDTH-1:0] out_dst_id;
    wire                out_valid;
    wire                out_last;
    wire                ready;

    // ------------------------------------------------------------------------
    // Testbench Variables
    // ------------------------------------------------------------------------
    integer pass_count;
    integer fail_count;
    integer initial_fail_count;
    integer wait_cnt;
    integer i;
    reg [255:0] current_test;

    // ------------------------------------------------------------------------
    // DUT Instantiation
    // ------------------------------------------------------------------------
    weight_decode #(
        .W_WIDTH   (W_WIDTH),
        .ID_WIDTH  (ID_WIDTH),
        .WE_AWIDTH (WE_AWIDTH),
        .WC_AWIDTH (WC_AWIDTH)
    ) dut (
        .clk           (clk),
        .rst_n         (rst_n),
        .req_neuron_id (req_neuron_id),
        .req_valid     (req_valid),
        .out_weight    (out_weight),
        .out_dst_id    (out_dst_id),
        .out_valid     (out_valid),
        .out_last      (out_last),
        .ready         (ready)
    );

    // ------------------------------------------------------------------------
    // Clock Generation
    // ------------------------------------------------------------------------
    initial begin
        clk = 1'b0;
        forever #(CLK_PERIOD / 2) clk = ~clk;
    end

    // ------------------------------------------------------------------------
    // VCD Dump
    // ------------------------------------------------------------------------
    initial begin
        $dumpfile("weight_decode.vcd");
        $dumpvars(0, tb_weight_decode);
    end

    // ------------------------------------------------------------------------
    // Checking Logic Tasks
    // ------------------------------------------------------------------------
    task verify_output;
        input [W_WIDTH-1:0]  exp_weight;
        input [ID_WIDTH-1:0] exp_dst_id;
        input                exp_last;
        begin
            if ((out_weight !== exp_weight) || (out_dst_id !== exp_dst_id) || (out_last !== exp_last)) begin
                $display("[%0t] [FAIL] %s | Exp: W=%0d ID=%0d L=%0b | Got: W=%0d ID=%0d L=%0b", 
                         $time, current_test, exp_weight, exp_dst_id, exp_last, out_weight, out_dst_id, out_last);
                fail_count = fail_count + 1;
            end else begin
                $display("[%0t] [PASS] %s", $time, current_test);
                pass_count = pass_count + 1;
            end
        end
    endtask

    task wait_for_valid;
        begin
            wait_cnt = 0;
            while (!out_valid && wait_cnt < TIMEOUT) begin
                @(negedge clk);
                wait_cnt = wait_cnt + 1;
            end
            if (wait_cnt >= TIMEOUT) begin
                $display("[%0t] [FAIL] %s | TIMEOUT: out_valid did not assert within %0d cycles.", $time, current_test, TIMEOUT);
                fail_count = fail_count + 1;
            end
        end
    endtask

    task wait_for_ready;
        begin
            wait_cnt = 0;
            while (!ready && wait_cnt < TIMEOUT) begin
                // If out_valid asserts unexpectedly while waiting for ready
                if (out_valid) begin
                    $display("[%0t] [FAIL] %s | out_valid asserted unexpectedly while waiting for ready!", $time, current_test);
                    fail_count = fail_count + 1;
                end
                @(negedge clk);
                wait_cnt = wait_cnt + 1;
            end
            
            if (wait_cnt >= TIMEOUT) begin
                $display("[%0t] [FAIL] %s | TIMEOUT: FSM did not return to ready within %0d cycles.", $time, current_test, TIMEOUT);
                fail_count = fail_count + 1;
            end else begin
                $display("[%0t] [PASS] %s", $time, current_test);
                pass_count = pass_count + 1;
            end
        end
    endtask

    // ------------------------------------------------------------------------
    // Main Verification Sequence
    // ------------------------------------------------------------------------
    initial begin
        pass_count = 0;
        fail_count = 0;
        
        req_neuron_id = 0;
        req_valid     = 0;
        
        // Assert Reset
        rst_n = 1'b0;
        #(CLK_PERIOD * 2);
        rst_n = 1'b1;

        $display("=================================================");
        $display(" Starting Verification: weight_decode");
        $display("=================================================");

        // --------------------------------------------------------------------
        // TEST 0: Reset State Verification
        // --------------------------------------------------------------------
        current_test = "Verify ready == 1 immediately after reset";
        if (ready !== 1'b1) begin
            $display("[%0t] [FAIL] %s | Expected ready=1, Got ready=0", $time, current_test);
            fail_count = fail_count + 1;
        end else begin
            $display("[%0t] [PASS] %s", $time, current_test);
            pass_count = pass_count + 1;
        end

        // --------------------------------------------------------------------
        // TEST 1: Zero Connections (Early Exit Check)
        // --------------------------------------------------------------------
        current_test = "Neuron 0 (0 connections) - FSM should return to IDLE without out_valid";
        @(negedge clk);
        req_neuron_id = 10'd0;
        req_valid     = 1'b1;
        @(negedge clk);
        req_valid     = 1'b0;
        
        // Wait for FSM to process and return to IDLE (also checks for unexpected out_valid)
        wait_for_ready();

        // --------------------------------------------------------------------
        // TEST 2: Single Connection & Ready=0 Check & Pulse Width Check
        // --------------------------------------------------------------------
        current_test = "Neuron 1 (1 connection) - Checking output & out_last";
        @(negedge clk);
        req_neuron_id = 10'd1;
        req_valid     = 1'b1;
        @(negedge clk);
        req_valid     = 1'b0;

        current_test = "Verify ready == 0 while FSM is busy";
        if (ready !== 1'b0) begin
            $display("[%0t] [FAIL] %s | Expected ready=0, Got ready=1", $time, current_test);
            fail_count = fail_count + 1;
        end else begin
            $display("[%0t] [PASS] %s", $time, current_test);
            pass_count = pass_count + 1;
        end

        current_test = "Neuron 1 (1 connection) - Data Validation";
        wait_for_valid();
        verify_output(6'd11, 10'd111, 1'b1); // Exp: Weight 11, Dest 111, Last 1
        
        // Check that out_valid is strictly a 1-cycle pulse
        current_test = "Verify out_valid is a one-clock-cycle pulse";
        @(negedge clk);
        if (out_valid !== 1'b0) begin
            $display("[%0t] [FAIL] %s | out_valid remained high for multiple cycles!", $time, current_test);
            fail_count = fail_count + 1;
        end else begin
            $display("[%0t] [PASS] %s", $time, current_test);
            pass_count = pass_count + 1;
        end
        
        // Wait for FSM to return to IDLE safely
        current_test = "FSM returned to IDLE after 1-connection stream";
        wait_for_ready();

        // --------------------------------------------------------------------
        // TEST 3: Multiple Connections & Busy-Request Ignore Strengthening
        // --------------------------------------------------------------------
        current_test = "Neuron 2 (3 connections) - Checking output 1";
        @(negedge clk);
        req_neuron_id = 10'd2;
        req_valid     = 1'b1;
        @(negedge clk);
        req_valid     = 1'b0;

        // Inject an invalid request while FSM is busy
        @(negedge clk);
        req_neuron_id = 10'd99;
        req_valid     = 1'b1;
        @(negedge clk);
        req_valid     = 1'b0; 

        // Check Connection 1
        wait_for_valid();
        verify_output(6'd21, 10'd201, 1'b0); // Last = 0

        // Check Connection 2
        current_test = "Neuron 2 (3 connections) - Checking output 2";
        @(negedge clk); // Step past current valid
        wait_for_valid();
        verify_output(6'd22, 10'd202, 1'b0); // Last = 0

        // Check Connection 3
        current_test = "Neuron 2 (3 connections) - Checking output 3 (Last)";
        @(negedge clk); // Step past current valid
        wait_for_valid();
        verify_output(6'd23, 10'd203, 1'b1); // Last = 1

        // --------------------------------------------------------------------
        // TEST 4: Prove ignored request yields no extra outputs
        // --------------------------------------------------------------------
        current_test = "Verify request issued while busy was ignored (no ghost streams)";
        initial_fail_count = fail_count; 
        
        @(negedge clk); // Step past the last valid cycle
        for (i = 0; i < 20; i = i + 1) begin
            if (out_valid) begin
                $display("[%0t] [FAIL] %s | Unexpected out_valid detected!", $time, current_test);
                fail_count = fail_count + 1;
            end
            @(negedge clk);
        end
        
        // If fail_count hasn't increased, the loop passed cleanly
        if (fail_count == initial_fail_count) begin
            $display("[%0t] [PASS] %s", $time, current_test);
            pass_count = pass_count + 1;
        end

        // Verify FSM returned to IDLE safely
        current_test = "FSM returned to IDLE after multi-connection stream";
        wait_for_ready();

        // --------------------------------------------------------------------
        // Simulation Summary
        // --------------------------------------------------------------------
        $display("=================================================");
        if (fail_count == 0) begin
            $display(" [SUCCESS] All %0d checks PASSED!", pass_count);
        end else begin
            $display(" [FAILED] %0d out of %0d checks FAILED.", fail_count, (pass_count + fail_count));
        end
        $display("=================================================");
        
        #20 $finish;
    end

endmodule

sim/test_weight_decode/test_weight_decode.sim/sim_1/behav/xsim/weight_decode.vcd
$date
   Thu Jul  2 14:30:28 2026
$end

$version
  2024.2.0
  $dumpfile ("weight_decode.vcd") 
$end

$timescale
  1ps
$end

$scope module tb_weight_decode $end
$var reg 1 ! clk $end
$var reg 1 " rst_n $end
$var reg 10 # req_neuron_id [9:0] $end
$var reg 1 $ req_valid $end
$var wire 6 % out_weight [5:0] $end
$var wire 10 & out_dst_id [9:0] $end
$var wire 1 ' out_valid $end
$var wire 1 ( out_last $end
$var wire 1 ) ready $end
$var integer 32 * pass_count [31:0] $end
$var integer 32 + fail_count [31:0] $end
$var integer 32 , initial_fail_count [31:0] $end
$var integer 32 - wait_cnt [31:0] $end
$var integer 32 . i [31:0] $end
$var reg 256 / current_test [255:0] $end
$scope module dut $end
$var wire 1 0 clk $end
$var wire 1 1 rst_n $end
$var wire 10 2 req_neuron_id [9:0] $end
$var wire 1 3 req_valid $end
$var reg 6 4 out_weight [5:0] $end
$var reg 10 5 out_dst_id [9:0] $end
$var reg 1 6 out_valid $end
$var reg 1 7 out_last $end
$var wire 1 ) ready $end
$var reg 10 8 we_addr [9:0] $end
$var reg 1 9 we_ce $end
$var reg 1 : we_we $end
$var wire 25 ; we_rdata [24:0] $end
$var reg 15 < wc_addr [14:0] $end
$var reg 1 = wc_ce $end
$var reg 1 > wc_we $end
$var wire 16 ? wc_rdata [15:0] $end
$var reg 3 @ state [2:0] $end
$var reg 15 A connection_addr [14:0] $end
$var reg 10 B remaining_connections [9:0] $end
$scope module u_went $end
$var wire 1 0 clk $end
$var wire 1 C ce $end
$var wire 1 D we $end
$var wire 10 E addr [9:0] $end
$var wire 25 F wdata [24:0] $end
$var reg 25 G rdata [24:0] $end
$var integer 32 H idx [31:0] $end
$upscope $end
$scope module u_wcon $end
$var wire 1 0 clk $end
$var wire 1 I ce $end
$var wire 1 J we $end
$var wire 15 K addr [14:0] $end
$var wire 16 L wdata [15:0] $end
$var reg 16 M rdata [15:0] $end
$var integer 32 N idx [31:0] $end
$upscope $end
$upscope $end
$scope task verify_output $end
$var reg 6 O exp_weight [5:0] $end
$var reg 10 P exp_dst_id [9:0] $end
$var reg 1 Q exp_last $end
$upscope $end
$scope task wait_for_valid $end
$upscope $end
$scope task wait_for_ready $end
$upscope $end
$upscope $end
$enddefinitions $end

#0
$dumpvars
0!
0"
b0 #
0$
b0 %
b0 &
0'
0(
1)
b0 *
b0 +
bx ,
bx -
bx .
bx /
00
01
b0 2
03
b0 4
b0 5
06
07
b0 8
09
0:
bx ;
b0 <
0=
0>
bx ?
b0 @
b0 A
b0 B
0C
0D
b0 E
b0 F
bx G
b10000000000 H
0I
0J
b0 K
b0 L
bx M
b1000000000000000 N
bx O
bx P
xQ
$end

#5000
1!
10

#10000
0!
00

#15000
1!
10

#20000
0!
1"
1$
b1 *
b111001001100101011101000111010101110010011011100010000001110100011011110010000001001001010001000100110001000101001000000111011101101001011101000110100001101111011101010111010000100000011011110111010101110100010111110111011001100001011011000110100101100100 /
00
11
13

#25000
1!
0)
10
19
b1 @
1C

#30000
0!
0$
b0 -
00
03

#35000
1!
10
09
b1000000 ;
b10 @
0C
b1000000 G

#40000
0!
b1 -
00

#45000
1!
10
1=
b11 @
b1000000 B
1I

#50000
0!
b10 -
00

#55000
1!
10
0=
b1111000001100010 ?
b100 @
0I
b1111000001100010 M

#60000
0!
b11 -
00

#65000
1!
b111100 %
b1100010 &
1'
10
b111100 4
b1100010 5
16
b1 <
1=
b11 @
b1 A
b111111 B
1I
b1 K

#70000
0!
b1 +
b100 -
00

#75000
1!
0'
10
06
0=
b1010001100011 ?
b100 @
0I
b1010001100011 M

#80000
0!
b101 -
00

#85000
1!
b101 %
b1100011 &
1'
10
b101 4
b1100011 5
16
b10 <
1=
b11 @
b10 A
b111110 B
1I
b10 K

#90000
0!
b10 +
b110 -
00

#95000
1!
0'
10
06
0=
b10010001100100 ?
b100 @
0I
b10010001100100 M

#100000
0!
b111 -
00

#105000
1!
b1001 %
b1100100 &
1'
10
b1001 4
b1100100 5
16
b11 <
1=
b11 @
b11 A
b111101 B
1I
b11 K

#110000
0!
b11 +
b1000 -
00

#115000
1!
0'
10
06
0=
b1100001100110 ?
b100 @
0I
b1100001100110 M

#120000
0!
b1001 -
00

#125000
1!
b110 %
b1100110 &
1'
10
b110 4
b1100110 5
16
b100 <
1=
b11 @
b100 A
b111100 B
1I
b100 K

#130000
0!
b100 +
b1010 -
00

#135000
1!
0'
10
06
0=
b1000001100111 ?
b100 @
0I
b1000001100111 M

#140000
0!
b1011 -
00

#145000
1!
b100 %
b1100111 &
1'
10
b100 4
b1100111 5
16
b101 <
1=
b11 @
b101 A
b111011 B
1I
b101 K

#150000
0!
b101 +
b1100 -
00

#155000
1!
0'
10
06
0=
b1110000001101100 ?
b100 @
0I
b1110000001101100 M

#160000
0!
b1101 -
00

#165000
1!
b111000 %
b1101100 &
1'
10
b111000 4
b1101100 5
16
b110 <
1=
b11 @
b110 A
b111010 B
1I
b110 K

#170000
0!
b110 +
b1110 -
00

#175000
1!
0'
10
06
0=
b10100001101111 ?
b100 @
0I
b10100001101111 M

#180000
0!
b1111 -
00

#185000
1!
b1010 %
b1101111 &
1'
10
b1010 4
b1101111 5
16
b111 <
1=
b11 @
b111 A
b111001 B
1I
b111 K

#190000
0!
b111 +
b10000 -
00

#195000
1!
0'
10
06
0=
b1010001110100 ?
b100 @
0I
b1010001110100 M

#200000
0!
b10001 -
00

#205000
1!
b101 %
b1110100 &
1'
10
b101 4
b1110100 5
16
b1000 <
1=
b11 @
b1000 A
b111000 B
1I
b1000 K

#210000
0!
b1000 +
b10010 -
00

#215000
1!
0'
10
06
0=
b1111000001110111 ?
b100 @
0I
b1111000001110111 M

#220000
0!
b10011 -
00

#225000
1!
b111100 %
b1110111 &
1'
10
b111100 4
b1110111 5
16
b1001 <
1=
b11 @
b1001 A
b110111 B
1I
b1001 K

#230000
0!
b1001 +
b10100 -
00

#235000
1!
0'
10
06
0=
b1000001111000 ?
b100 @
0I
b1000001111000 M

#240000
0!
b10101 -
00

#245000
1!
b100 %
b1111000 &
1'
10
b100 4
b1111000 5
16
b1010 <
1=
b11 @
b1010 A
b110110 B
1I
b1010 K

#250000
0!
b1010 +
b10110 -
00

#255000
1!
0'
10
06
0=
b1110001111111 ?
b100 @
0I
b1110001111111 M

#260000
0!
b10111 -
00

#265000
1!
b111 %
b1111111 &
1'
10
b111 4
b1111111 5
16
b1011 <
1=
b11 @
b1011 A
b110101 B
1I
b1011 K

#270000
0!
b1011 +
b11000 -
00

#275000
1!
0'
10
06
0=
b1100010001010 ?
b100 @
0I
b1100010001010 M

#280000
0!
b11001 -
00

#285000
1!
b110 %
b10001010 &
1'
10
b110 4
b10001010 5
16
b1100 <
1=
b11 @
b1100 A
b110100 B
1I
b1100 K

#290000
0!
b1100 +
b11010 -
00

#295000
1!
0'
10
06
0=
b1110100010001110 ?
b100 @
0I
b1110100010001110 M

#300000
0!
b11011 -
00

#305000
1!
b111010 %
b10001110 &
1'
10
b111010 4
b10001110 5
16
b1101 <
1=
b11 @
b1101 A
b110011 B
1I
b1101 K

#310000
0!
b1101 +
b11100 -
00

#315000
1!
0'
10
06
0=
b1000010010100 ?
b100 @
0I
b1000010010100 M

#320000
0!
b11101 -
00

#325000
1!
b100 %
b10010100 &
1'
10
b100 4
b10010100 5
16
b1110 <
1=
b11 @
b1110 A
b110010 B
1I
b1110 K

#330000
0!
b1110 +
b11110 -
00

#335000
1!
0'
10
06
0=
b1000010011000 ?
b100 @
0I
b1000010011000 M

#340000
0!
b11111 -
00

#345000
1!
b10011000 &
1'
10
b10011000 5
16
b1111 <
1=
b11 @
b1111 A
b110001 B
1I
b1111 K

#350000
0!
b1111 +
b100000 -
00

#355000
1!
0'
10
06
0=
b1010010011001 ?
b100 @
0I
b1010010011001 M

#360000
0!
b100001 -
00

#365000
1!
b101 %
b10011001 &
1'
10
b101 4
b10011001 5
16
b10000 <
1=
b11 @
b10000 A
b110000 B
1I
b10000 K

#370000
0!
b10000 +
b100010 -
00

#375000
1!
0'
10
06
0=
b1101110010011011 ?
b100 @
0I
b1101110010011011 M

#380000
0!
b100011 -
00

#385000
1!
b110111 %
b10011011 &
1'
10
b110111 4
b10011011 5
16
b10001 <
1=
b11 @
b10001 A
b101111 B
1I
b10001 K

#390000
0!
b10001 +
b100100 -
00

#395000
1!
0'
10
06
0=
b1000010100011 ?
b100 @
0I
b1000010100011 M

#400000
0!
b100101 -
00

#405000
1!
b100 %
b10100011 &
1'
10
b100 4
b10100011 5
16
b10010 <
1=
b11 @
b10010 A
b101110 B
1I
b10010 K

#410000
0!
b10010 +
b100110 -
00

#415000
1!
0'
10
06
0=
b1110100010110000 ?
b100 @
0I
b1110100010110000 M

#420000
0!
b100111 -
00

#425000
1!
b111010 %
b10110000 &
1'
10
b111010 4
b10110000 5
16
b10011 <
1=
b11 @
b10011 A
b101101 B
1I
b10011 K

#430000
0!
b10011 +
b101000 -
00

#435000
1!
0'
10
06
0=
b10110010110011 ?
b100 @
0I
b10110010110011 M

#440000
0!
b101001 -
00

#445000
1!
b1011 %
b10110011 &
1'
10
b1011 4
b10110011 5
16
b10100 <
1=
b11 @
b10100 A
b101100 B
1I
b10100 K

#450000
0!
b10100 +
b101010 -
00

#455000
1!
0'
10
06
0=
b1101110010110101 ?
b100 @
0I
b1101110010110101 M

#460000
0!
b101011 -
00

#465000
1!
b110111 %
b10110101 &
1'
10
b110111 4
b10110101 5
16
b10101 <
1=
b11 @
b10101 A
b101011 B
1I
b10101 K

#470000
0!
b10101 +
b101100 -
00

#475000
1!
0'
10
06
0=
b1000010110111 ?
b100 @
0I
b1000010110111 M

#480000
0!
b101101 -
00

#485000
1!
b100 %
b10110111 &
1'
10
b100 4
b10110111 5
16
b10110 <
1=
b11 @
b10110 A
b101010 B
1I
b10110 K

#490000
0!
b10110 +
b101110 -
00

#495000
1!
0'
10
06
0=
b1100010111000 ?
b100 @
0I
b1100010111000 M

#500000
0!
b101111 -
00

#505000
1!
b110 %
b10111000 &
1'
10
b110 4
b10111000 5
16
b10111 <
1=
b11 @
b10111 A
b101001 B
1I
b10111 K

#510000
0!
b10111 +
b110000 -
00

#515000
1!
0'
10
06
0=
b1100010111001 ?
b100 @
0I
b1100010111001 M

#520000
0!
b110001 -
00

#525000
1!
b10111001 &
1'
10
b10111001 5
16
b11000 <
1=
b11 @
b11000 A
b101000 B
1I
b11000 K

#530000
0!
b11000 +
b110010 -
b110111101101110001010010010000000101101001000000100001101101000011001010110001101101011011010010110111001100111001000000110111101110101011101000111000001110101011101000010000000100110001000000110111101110101011101000101111101101100011000010111001101110100 /
00

#535000
1!
0'
10
06
0=
b1000010111010 ?
b100 @
0I
b1000010111010 M

#540000
0!
b1 #
1$
00
b1 2
13

#545000
1!
b100 %
b10111010 &
1'
10
b100 4
b10111010 5
16
b11001 <
1=
b11 @
b11001 A
b100111 B
1I
b11001 K

#550000
0!
0$
b10 *
b11001 +
b0 -
b111011001100001011011000110100101100100001000000110100101110011001000000110000100100000011011110110111001100101001011010110001101101100011011110110001101101011001011010110001101111001011000110110110001100101001000000111000001110101011011000111001101100101 /
00
03
b1011 O
b1101111 P
1Q

#555000
1!
0'
10
06
0=
b1000010111011 ?
b100 @
0I
b1000010111011 M

#560000
0!
b11 *
b110111100100000010010010100010001001100010001010010000001100001011001100111010001100101011100100010000000110001001011010110001101101111011011100110111001100101011000110111010001101001011011110110111000100000011100110111010001110010011001010110000101101101 /
00

#565000
1!
b10111011 &
1'
10
b10111011 5
16
b11010 <
1=
b11 @
b11010 A
b100110 B
1I
b11010 K

#570000
0!
b11010 +
b1 -
00

#575000
1!
0'
10
06
0=
b1111000010111100 ?
b100 @
0I
b1111000010111100 M

#580000
0!
b10 -
00

#585000
1!
b111100 %
b10111100 &
1'
10
b111100 4
b10111100 5
16
b11011 <
1=
b11 @
b11011 A
b100101 B
1I
b11011 K

#590000
0!
b11011 +
b11 -
00

#595000
1!
0'
10
06
0=
b1110100010111101 ?
b100 @
0I
b1110100010111101 M

#600000
0!
b100 -
00

#605000
1!
b111010 %
b10111101 &
1'
10
b111010 4
b10111101 5
16
b11100 <
1=
b11 @
b11100 A
b100100 B
1I
b11100 K

#610000
0!
b11100 +
b101 -
00

#615000
1!
0'
10
06
0=
b1110100011000001 ?
b100 @
0I
b1110100011000001 M

#620000
0!
b110 -
00

#625000
1!
b11000001 &
1'
10
b11000001 5
16
b11101 <
1=
b11 @
b11101 A
b100011 B
1I
b11101 K

#630000
0!
b11101 +
b111 -
00

#635000
1!
0'
10
06
0=
b1111000011000010 ?
b100 @
0I
b1111000011000010 M

#640000
0!
b1000 -
00

#645000
1!
b111100 %
b11000010 &
1'
10
b111100 4
b11000010 5
16
b11110 <
1=
b11 @
b11110 A
b100010 B
1I
b11110 K

#650000
0!
b11110 +
b1001 -
00

#655000
1!
0'
10
06
0=
b1000011000101 ?
b100 @
0I
b1000011000101 M

#660000
0!
b1010 -
00

#665000
1!
b100 %
b11000101 &
1'
10
b100 4
b11000101 5
16
b11111 <
1=
b11 @
b11111 A
b100001 B
1I
b11111 K

#670000
0!
b11111 +
b1011 -
00

#675000
1!
0'
10
06
0=
b1000011000111 ?
b100 @
0I
b1000011000111 M

#680000
0!
b1100 -
00

#685000
1!
b11000111 &
1'
10
b11000111 5
16
b100000 <
1=
b11 @
b100000 A
b100000 B
1I
b100000 K

#690000
0!
b100000 +
b1101 -
00

#695000
1!
0'
10
06
0=
b1110011001111 ?
b100 @
0I
b1110011001111 M

#700000
0!
b1110 -
00

#705000
1!
b111 %
b11001111 &
1'
10
b111 4
b11001111 5
16
b100001 <
1=
b11 @
b100001 A
b11111 B
1I
b100001 K

#710000
0!
b100001 +
b1111 -
00

#715000
1!
0'
10
06
0=
b1010011010000 ?
b100 @
0I
b1010011010000 M

#720000
0!
b10000 -
00

#725000
1!
b101 %
b11010000 &
1'
10
b101 4
b11010000 5
16
b100010 <
1=
b11 @
b100010 A
b11110 B
1I
b100010 K

#730000
0!
b100010 +
b10001 -
00

#735000
1!
0'
10
06
0=
b1000011010010 ?
b100 @
0I
b1000011010010 M

#740000
0!
b10010 -
00

#745000
1!
b100 %
b11010010 &
1'
10
b100 4
b11010010 5
16
b100011 <
1=
b11 @
b100011 A
b11101 B
1I
b100011 K

#750000
0!
b100011 +
b10011 -
00

#755000
1!
0'
10
06
0=
b1111000011010100 ?
b100 @
0I
b1111000011010100 M

#760000
0!
b10100 -
00

#765000
1!
b111100 %
b11010100 &
1'
10
b111100 4
b11010100 5
16
b100100 <
1=
b11 @
b100100 A
b11100 B
1I
b100100 K

#770000
0!
b100100 +
b10101 -
00

#775000
1!
0'
10
06
0=
b1000011010110 ?
b100 @
0I
b1000011010110 M

#780000
0!
b10110 -
00

#785000
1!
b100 %
b11010110 &
1'
10
b100 4
b11010110 5
16
b100101 <
1=
b11 @
b100101 A
b11011 B
1I
b100101 K

#790000
0!
b100101 +
b10111 -
00

