rtl/compute/spike_iterator.v
`timescale 1ns/1ps

// ============================================================================
// Project      : SNN_ECG_V2
// Module       : spike_iterator
// Description  : Hardware scanner that serializes a 1024-bit parallel 
//                spike bus into a sequence of active neuron identifiers.
//                Implements a snapshot-and-scan mechanism.
// ============================================================================

module spike_iterator #(
    parameter N          = 1024,
    parameter ID_WIDTH   = 10
)(
    input  wire                 clk,
    input  wire                 rst_n,
    
    // Spike bus input
    input  wire [N-1:0]         spike_bus,
    input  wire                 start,
    
    // Serialized output stream
    output reg  [ID_WIDTH-1:0]  neuron_id,
    output reg                  valid,
    output reg                  done
);

    // ========================================================================
    // Internal Registers
    // ========================================================================
    reg [ID_WIDTH-1:0] ptr;
    reg                active;
    reg [N-1:0]        spike_snapshot;

    // ========================================================================
    // Scan Logic
    // ========================================================================
    always @(posedge clk or negedge rst_n) begin
        if (!rst_n) begin
            ptr            <= {ID_WIDTH{1'b0}};
            active         <= 1'b0;
            valid          <= 1'b0;
            done           <= 1'b0;
            neuron_id      <= {ID_WIDTH{1'b0}};
            spike_snapshot <= {N{1'b0}};
        end else begin
            // Reset control pulses each cycle
            valid <= 1'b0;
            done  <= 1'b0;

            if (start) begin
                // Latch the current spike bus state to prevent race conditions 
                // during the scan serialization process.
                spike_snapshot <= spike_bus;
                ptr            <= {ID_WIDTH{1'b0}};
                active         <= 1'b1;
            end else if (active) begin
                // Identify the firing neuron at the current pointer index
                if (spike_snapshot[ptr]) begin
                    neuron_id <= ptr;
                    valid     <= 1'b1;
                end
                
                // Advance pointer and check for scan completion
                if (ptr == N - 1) begin
                    done   <= 1'b1;
                    active <= 1'b0;
                    ptr    <= {ID_WIDTH{1'b0}};
                end else begin
                    ptr <= ptr + 1;
                end
            end
        end
    end

endmodule

tb/tb_spike_iterator.v
`timescale 1ns/1ps

module tb_spike_iterator;

    // ==================================================
    // PARAMETERS
    // ==================================================
    parameter CLK_PERIOD = 10;
    parameter N          = 1024;
    parameter ID_WIDTH   = 10;

    // ==================================================
    // DUT SIGNALS
    // ==================================================
    reg                 clk;
    reg                 rst_n;
    reg  [N-1:0]        spike_bus;
    reg                 start;

    wire [ID_WIDTH-1:0] neuron_id;
    wire                valid;
    wire                done;

    // ==================================================
    // TESTBENCH CONTROL SIGNALS
    // ==================================================
    integer pass_count;
    integer fail_count;
    integer test_id;
    integer err_cnt;
    integer i;

    reg [N-1:0] test_pattern;

    // ==================================================
    // DUT INSTANTIATION
    // ==================================================
    spike_iterator #(
        .N(N),
        .ID_WIDTH(ID_WIDTH)
    ) u_dut (
        .clk        (clk),
        .rst_n      (rst_n),
        .spike_bus  (spike_bus),
        .start      (start),
        .neuron_id  (neuron_id),
        .valid      (valid),
        .done       (done)
    );

    // ==================================================
    // CLOCK GENERATION
    // ==================================================
    initial begin
        clk = 1'b0;
        forever #(CLK_PERIOD / 2.0) clk = ~clk;
    end

    // ==================================================
    // HELPER TASKS
    // ==================================================

    // --------------------------------------------------
    // Task: System Reset
    // --------------------------------------------------
    task apply_reset;
    begin
        rst_n     = 1'b0;
        start     = 1'b0;
        spike_bus = {N{1'b0}};
        
        #(CLK_PERIOD * 5);
        @(negedge clk);
        rst_n = 1'b1;
        #(CLK_PERIOD * 2);
    end
    endtask

    // --------------------------------------------------
    // Task: Run Scan and Verify Cycle-by-Cycle
    // --------------------------------------------------
    task run_and_check;
        input [N-1:0] pattern;
        input         change_mid_scan;
        
        integer idx;
        integer local_errors;
    begin
        local_errors = 0;
        
        @(negedge clk);
        spike_bus = pattern;
        start     = 1'b1;
        
        @(negedge clk);
        start = 1'b0;
        
        // The RTL scans exactly 1 neuron per cycle for N cycles
        for (idx = 0; idx < N; idx = idx + 1) begin
            @(negedge clk);
            
            // Snapshot Verification: Change input bus completely at midway point
            if (change_mid_scan && (idx == (N / 2))) begin
                spike_bus = ~pattern;
            end
            
            // Check for X or Z states
            if (valid === 1'bx || valid === 1'bz || done === 1'bx || done === 1'bz) begin
                local_errors = local_errors + 1;
                $display("[FAIL] Test %0d: X or Z state detected at index %0d.", test_id, idx);
            end
            
            // Verify 'valid' and 'neuron_id' based on original pattern
            if (pattern[idx] === 1'b1) begin
                if (valid !== 1'b1) begin
                    local_errors = local_errors + 1;
                    $display("[FAIL] Test %0d: valid missing at index %0d.", test_id, idx);
                end
                if (neuron_id !== idx) begin
                    local_errors = local_errors + 1;
                    $display("[FAIL] Test %0d: ID mismatch. Exp: %0d, Got: %0d", test_id, idx, neuron_id);
                end
            end else begin
                if (valid !== 1'b0) begin
                    local_errors = local_errors + 1;
                    $display("[FAIL] Test %0d: valid incorrectly high at index %0d.", test_id, idx);
                end
            end
            
            // Verify 'done' timing (only high on the very last cycle of scan)
            if (idx == N - 1) begin
                if (done !== 1'b1) begin
                    local_errors = local_errors + 1;
                    $display("[FAIL] Test %0d: done NOT asserted at end of scan.", test_id);
                end
            end else begin
                if (done !== 1'b0) begin
                    local_errors = local_errors + 1;
                    $display("[FAIL] Test %0d: done asserted early at index %0d.", test_id, idx);
                end
            end
        end
        
        // Verify pulse widths (1 cycle only)
        @(negedge clk);
        if (done !== 1'b0) begin
            local_errors = local_errors + 1;
            $display("[FAIL] Test %0d: done pulse wider than 1 cycle.", test_id);
        end
        if (valid !== 1'b0) begin
            local_errors = local_errors + 1;
            $display("[FAIL] Test %0d: valid pulse wider than 1 cycle.", test_id);
        end
        
        if (local_errors == 0) begin
            pass_count = pass_count + 1;
            $display("[PASS] Test %0d: Scan verified successfully.", test_id);
        end else begin
            fail_count = fail_count + 1;
            $display("[FAIL] Test %0d: Scan failed with %0d errors.", test_id, local_errors);
        end
        
        // Restore bus to zero
        spike_bus = {N{1'b0}};
    end
    endtask

    // ==================================================
    // MAIN TEST SEQUENCE
    // ==================================================
    initial begin
        // Initialize
        pass_count = 0;
        fail_count = 0;
        test_id    = 0;

        // VCD Dumping
        $dumpfile("spike_iterator.vcd");
        $dumpvars(0, tb_spike_iterator);

        // --------------------------------------------------
        // TEST 1: Reset Behavior
        // --------------------------------------------------
        test_id = 1;
        apply_reset();
        @(negedge clk);
        
        if (valid !== 1'b0 || done !== 1'b0 || neuron_id !== 0) begin
            fail_count = fail_count + 1;
            $display("[FAIL] Test %0d: Outputs not fully cleared after reset.", test_id);
        end else begin
            pass_count = pass_count + 1;
            $display("[PASS] Test %0d: Reset cleared all outputs correctly.", test_id);
        end

        // --------------------------------------------------
        // TEST 2: Empty Spike Bus
        // --------------------------------------------------
        test_id = 2;
        test_pattern = {N{1'b0}};
        run_and_check(test_pattern, 1'b0);

        // --------------------------------------------------
        // TEST 3: Single Spike (Mid-range)
        // --------------------------------------------------
        test_id = 3;
        test_pattern = {N{1'b0}};
        test_pattern[512] = 1'b1;
        run_and_check(test_pattern, 1'b0);

        // --------------------------------------------------
        // TEST 4: Multiple Sparse Spikes
        // --------------------------------------------------
        test_id = 4;
        test_pattern = {N{1'b0}};
        test_pattern[10]  = 1'b1;
        test_pattern[256] = 1'b1;
        test_pattern[789] = 1'b1;
        run_and_check(test_pattern, 1'b0);

        // --------------------------------------------------
        // TEST 5: Consecutive Spikes (Burst)
        // --------------------------------------------------
        test_id = 5;
        test_pattern = {N{1'b0}};
        test_pattern[100] = 1'b1;
        test_pattern[101] = 1'b1;
        test_pattern[102] = 1'b1;
        test_pattern[103] = 1'b1;
        run_and_check(test_pattern, 1'b0);

        // --------------------------------------------------
        // TEST 6: Boundary Addresses (0 and 1023)
        // --------------------------------------------------
        test_id = 6;
        test_pattern = {N{1'b0}};
        test_pattern[0]   = 1'b1;
        test_pattern[N-1] = 1'b1;
        run_and_check(test_pattern, 1'b0);

        // --------------------------------------------------
        // TEST 7: Dense Spike Bus (All 1s)
        // --------------------------------------------------
        test_id = 7;
        test_pattern = {N{1'b1}};
        run_and_check(test_pattern, 1'b0);

        // --------------------------------------------------
        // TEST 8: Snapshot Verification
        // --------------------------------------------------
        test_id = 8;
        test_pattern = {N{1'b0}};
        test_pattern[10]  = 1'b1;
        test_pattern[800] = 1'b1;
        // The task will invert the input bus at cycle N/2 to ensure outputs remain unaffected
        run_and_check(test_pattern, 1'b1);

        // --------------------------------------------------
        // SUMMARY
        // --------------------------------------------------
        $display("========================================");
        $display("PASSED : %0d", pass_count);
        $display("FAILED : %0d", fail_count);
        $display("========================================");
        
        $finish;
    end

endmodule

sim/test_spike_iterator/test_spike_iterator.sim/sim_1/behav/xsim/spike_iterator.vcd
$date
   Thu Jul  2 16:29:42 2026
$end

$version
  2024.2.0
  $dumpfile ("spike_iterator.vcd") 
$end

$timescale
  1ps
$end

$scope module tb_spike_iterator $end
$var reg 1 ! clk $end
$var reg 1 " rst_n $end
$var reg 1024 # spike_bus [1023:0] $end
$var reg 1 $ start $end
$var wire 10 % neuron_id [9:0] $end
$var wire 1 & valid $end
$var wire 1 ' done $end
$var integer 32 ( pass_count [31:0] $end
$var integer 32 ) fail_count [31:0] $end
$var integer 32 * test_id [31:0] $end
$var integer 32 + err_cnt [31:0] $end
$var integer 32 , i [31:0] $end
$var reg 1024 - test_pattern [1023:0] $end
$scope module u_dut $end
$var wire 1 . clk $end
$var wire 1 / rst_n $end
$var wire 1024 0 spike_bus [1023:0] $end
$var wire 1 1 start $end
$var reg 10 2 neuron_id [9:0] $end
$var reg 1 3 valid $end
$var reg 1 4 done $end
$var reg 10 5 ptr [9:0] $end
$var reg 1 6 active $end
$var reg 1024 7 spike_snapshot [1023:0] $end
$upscope $end
$scope task apply_reset $end
$upscope $end
$scope task run_and_check $end
$var reg 1024 8 pattern [1023:0] $end
$var reg 1 9 change_mid_scan $end
$var integer 32 : idx [31:0] $end
$var integer 32 ; local_errors [31:0] $end
$upscope $end
$upscope $end
$enddefinitions $end

#0
$dumpvars
0!
0"
b0 #
0$
b0 %
0&
0'
b0 (
b0 )
b1 *
bx +
bx ,
bx -
0.
0/
b0 0
01
b0 2
03
04
b0 5
06
b0 7
bx 8
x9
bx :
bx ;
$end

#5000
1!
1.

#10000
0!
0.

#15000
1!
1.

#20000
0!
0.

#25000
1!
1.

#30000
0!
0.

#35000
1!
1.

#40000
0!
0.

#45000
1!
1.

#50000
0!
1"
0.
1/

#55000
1!
1.

#60000
0!
0.

#65000
1!
1.

#70000
0!
b1 (
b10 *
b0 -
0.
b0 8
09
b0 ;

#75000
1!
1.

#80000
0!
1$
0.
11

#85000
1!
1.
16

#90000
0!
0$
0.
01
b0 :

#95000
1!
1.
b1 5

#100000
0!
0.
b1 :

#105000
1!
1.
b10 5

#110000
0!
0.
b10 :

#115000
1!
1.
b11 5

#120000
0!
0.
b11 :

#125000
1!
1.
b100 5

#130000
0!
0.
b100 :

#135000
1!
1.
b101 5

#140000
0!
0.
b101 :

#145000
1!
1.
b110 5

#150000
0!
0.
b110 :

#155000
1!
1.
b111 5

#160000
0!
0.
b111 :

#165000
1!
1.
b1000 5

#170000
0!
0.
b1000 :

#175000
1!
1.
b1001 5

#180000
0!
0.
b1001 :

#185000
1!
1.
b1010 5

#190000
0!
0.
b1010 :

#195000
1!
1.
b1011 5

#200000
0!
0.
b1011 :

#205000
1!
1.
b1100 5

#210000
0!
0.
b1100 :

#215000
1!
1.
b1101 5

#220000
0!
0.
b1101 :

#225000
1!
1.
b1110 5

#230000
0!
0.
b1110 :

#235000
1!
1.
b1111 5

#240000
0!
0.
b1111 :

#245000
1!
1.
b10000 5

#250000
0!
0.
b10000 :

#255000
1!
1.
b10001 5

#260000
0!
0.
b10001 :

#265000
1!
1.
b10010 5

#270000
0!
0.
b10010 :

#275000
1!
1.
b10011 5

#280000
0!
0.
b10011 :

#285000
1!
1.
b10100 5

#290000
0!
0.
b10100 :

#295000
1!
1.
b10101 5

#300000
0!
0.
b10101 :

#305000
1!
1.
b10110 5

#310000
0!
0.
b10110 :

#315000
1!
1.
b10111 5

#320000
0!
0.
b10111 :

#325000
1!
1.
b11000 5

#330000
0!
0.
b11000 :

#335000
1!
1.
b11001 5

#340000
0!
0.
b11001 :

#345000
1!
1.
b11010 5

#350000
0!
0.
b11010 :

#355000
1!
1.
b11011 5

#360000
0!
0.
b11011 :

#365000
1!
1.
b11100 5

#370000
0!
0.
b11100 :

#375000
1!
1.
b11101 5

#380000
0!
0.
b11101 :

#385000
1!
1.
b11110 5

#390000
0!
0.
b11110 :

#395000
1!
1.
b11111 5

#400000
0!
0.
b11111 :

#405000
1!
1.
b100000 5

#410000
0!
0.
b100000 :

#415000
1!
1.
b100001 5

#420000
0!
0.
b100001 :

#425000
1!
1.
b100010 5

#430000
0!
0.
b100010 :

#435000
1!
1.
b100011 5

#440000
0!
0.
b100011 :

#445000
1!
1.
b100100 5

#450000
0!
0.
b100100 :

#455000
1!
1.
b100101 5

#460000
0!
0.
b100101 :

#465000
1!
1.
b100110 5

#470000
0!
0.
b100110 :

#475000
1!
1.
b100111 5

#480000
0!
0.
b100111 :

#485000
1!
1.
b101000 5

#490000
0!
0.
b101000 :

#495000
1!
1.
b101001 5

#500000
0!
0.
b101001 :

#505000
1!
1.
b101010 5

#510000
0!
0.
b101010 :

#515000
1!
1.
b101011 5

#520000
0!
0.
b101011 :

#525000
1!
1.
b101100 5

#530000
0!
0.
b101100 :

#535000
1!
1.
b101101 5

#540000
0!
0.
b101101 :

#545000
1!
1.
b101110 5

#550000
0!
0.
b101110 :

#555000
1!
1.
b101111 5

#560000
0!
0.
b101111 :

#565000
1!
1.
b110000 5

#570000
0!
0.
b110000 :

#575000
1!
1.
b110001 5

#580000
0!
0.
b110001 :

#585000
1!
1.
b110010 5

#590000
0!
0.
b110010 :

#595000
1!
1.
b110011 5

#600000
0!
0.
b110011 :

#605000
1!
1.
b110100 5

#610000
0!
0.
b110100 :

#615000
1!
1.
b110101 5

#620000
0!
0.
b110101 :

#625000
1!
1.
b110110 5

#630000
0!
0.
b110110 :

#635000
1!
1.
b110111 5

#640000
0!
0.
b110111 :

#645000
1!
1.
b111000 5

#650000
0!
0.
b111000 :

#655000
1!
1.
b111001 5

#660000
0!
0.
b111001 :

#665000
1!
1.
b111010 5

#670000
0!
0.
b111010 :

#675000
1!
1.
b111011 5

#680000
0!
0.
b111011 :

#685000
1!
1.
b111100 5

#690000
0!
0.
b111100 :

#695000
1!
1.
b111101 5

#700000
0!
0.
b111101 :

#705000
1!
1.
b111110 5

#710000
0!
0.
b111110 :

#715000
1!
1.
b111111 5

#720000
0!
0.
b111111 :

#725000
1!
1.
b1000000 5

#730000
0!
0.
b1000000 :

#735000
1!
1.
b1000001 5

#740000
0!
0.
b1000001 :

#745000
1!
1.
b1000010 5

#750000
0!
0.
b1000010 :

#755000
1!
1.
b1000011 5

#760000
0!
0.
b1000011 :

#765000
1!
1.
b1000100 5

#770000
0!
0.
b1000100 :

#775000
1!
1.
b1000101 5

#780000
0!
0.
b1000101 :

#785000
1!
1.
b1000110 5

#790000
0!
0.
b1000110 :

#795000
1!
1.
b1000111 5

#800000
0!
0.
b1000111 :

#805000
1!
1.
b1001000 5

#810000
0!
0.
b1001000 :

#815000
1!
1.
b1001001 5

#820000
0!
0.
b1001001 :

#825000
1!
1.
b1001010 5

#830000
0!
0.
b1001010 :

#835000
1!
1.
b1001011 5

#840000
0!
0.
b1001011 :

#845000
1!
1.
b1001100 5

#850000
0!
0.
b1001100 :

#855000
1!
1.
b1001101 5

#860000
0!
0.
b1001101 :

#865000
1!
1.
b1001110 5

#870000
0!
0.
b1001110 :

#875000
1!
1.
b1001111 5

#880000
0!
0.
b1001111 :

#885000
1!
1.
b1010000 5

#890000
0!
0.
b1010000 :

#895000
1!
1.
b1010001 5

#900000
0!
0.
b1010001 :

#905000
1!
1.
b1010010 5

#910000
0!
0.
b1010010 :

#915000
1!
1.
b1010011 5

#920000
0!
0.
b1010011 :

#925000
1!
1.
b1010100 5

#930000
0!
0.
b1010100 :

#935000
1!
1.
b1010101 5

#940000
0!
0.
b1010101 :

#945000
1!
1.
b1010110 5

#950000
0!
0.
b1010110 :

#955000
1!
1.
b1010111 5

#960000
0!
0.
b1010111 :

#965000
1!
1.
b1011000 5

#970000
0!
0.
b1011000 :

#975000
1!
1.
b1011001 5

#980000
0!
0.
b1011001 :

#985000
1!
1.
b1011010 5

#990000
0!
0.
b1011010 :

#995000
1!
1.
b1011011 5

#1000000
0!
0.
b1011011 :

#1005000
1!
1.
b1011100 5

#1010000
0!
0.
b1011100 :

#1015000
1!
1.
b1011101 5

#1020000
0!
0.
b1011101 :

#1025000
1!
1.
b1011110 5

#1030000
0!
0.
b1011110 :

#1035000
1!
1.
b1011111 5

#1040000
0!
0.
b1011111 :

#1045000
1!
1.
b1100000 5

#1050000
0!
0.
b1100000 :

#1055000
1!
1.
b1100001 5

#1060000
0!
0.
b1100001 :

#1065000
1!
1.
b1100010 5

#1070000
0!
0.
b1100010 :

#1075000
1!
1.
b1100011 5

#1080000
0!
0.
b1100011 :

#1085000
1!
1.
b1100100 5

#1090000
0!
0.
b1100100 :

#1095000
1!
1.
b1100101 5

#1100000
0!
0.
b1100101 :

#1105000
1!
1.
b1100110 5

#1110000
0!
0.
b1100110 :

#1115000
1!
1.
b1100111 5

#1120000
0!
0.
b1100111 :

#1125000
1!
1.
b1101000 5

#1130000
0!
0.
b1101000 :

#1135000
1!
1.
b1101001 5

#1140000
0!
0.
b1101001 :

#1145000
1!
1.
b1101010 5

#1150000
0!
0.
b1101010 :

#1155000
1!
1.
b1101011 5

#1160000
0!
0.
b1101011 :

#1165000
1!
1.
b1101100 5

#1170000
0!
0.
b1101100 :

#1175000
1!
1.
b1101101 5

#1180000
0!
0.
b1101101 :

#1185000
1!
1.
b1101110 5

#1190000
0!
0.
b1101110 :

#1195000
1!
1.
b1101111 5

#1200000
0!
0.
b1101111 :

#1205000
1!
1.
b1110000 5

#1210000
0!
0.
b1110000 :

#1215000
1!
1.
b1110001 5

#1220000
0!
0.
b1110001 :

#1225000
1!
1.
b1110010 5

#1230000
0!
0.
b1110010 :

#1235000
1!
1.
b1110011 5

#1240000
0!
0.
b1110011 :

#1245000
1!
1.
b1110100 5

#1250000
0!
0.
b1110100 :

#1255000
1!
1.
b1110101 5

#1260000
0!
0.
b1110101 :

#1265000
1!
1.
b1110110 5

#1270000
0!
0.
b1110110 :

#1275000
1!
1.
b1110111 5

#1280000
0!
0.
b1110111 :

#1285000
1!
1.
b1111000 5

#1290000
0!
0.
b1111000 :

#1295000
1!
1.
b1111001 5

#1300000
0!
0.
b1111001 :

#1305000
1!
1.
b1111010 5

#1310000
0!
0.
b1111010 :

#1315000
1!
1.
b1111011 5

#1320000
0!
0.
b1111011 :

#1325000
1!
1.
b1111100 5

#1330000
0!
0.
b1111100 :

#1335000
1!
1.
b1111101 5

#1340000
0!
0.
b1111101 :

#1345000
1!
1.
b1111110 5

#1350000
0!
0.
b1111110 :

#1355000
1!
1.
b1111111 5

#1360000
0!
0.
b1111111 :

#1365000
1!
1.
b10000000 5

#1370000
0!
0.
b10000000 :

#1375000
1!
1.
b10000001 5

#1380000
0!
0.
b10000001 :

#1385000
1!
1.
b10000010 5

#1390000
0!
0.
b10000010 :

#1395000
1!
1.
b10000011 5

#1400000
0!
0.
b10000011 :

#1405000
1!
1.
b10000100 5

#1410000
0!
0.
b10000100 :

#1415000
1!
1.
b10000101 5

#1420000
0!
0.
b10000101 :

#1425000
1!
1.
b10000110 5

#1430000
0!
0.
b10000110 :

#1435000
1!
1.
b10000111 5

#1440000
0!
0.
b10000111 :

#1445000
1!
1.
b10001000 5

#1450000
0!
0.
b10001000 :

#1455000
1!
1.
b10001001 5

#1460000
0!
0.
b10001001 :

#1465000
1!
1.
b10001010 5

#1470000
0!
0.
b10001010 :

#1475000
1!
1.
b10001011 5

#1480000
0!
0.
b10001011 :

#1485000
1!
1.
b10001100 5

#1490000
0!
0.
b10001100 :

#1495000
1!
1.
b10001101 5

#1500000
0!
0.
b10001101 :

#1505000
1!
1.
b10001110 5

#1510000
0!
0.
b10001110 :

#1515000
1!
1.
b10001111 5

#1520000
0!
0.
b10001111 :

#1525000
1!
1.
b10010000 5

#1530000
0!
0.
b10010000 :

#1535000
1!
1.
b10010001 5

#1540000
0!
0.
b10010001 :

#1545000
1!
1.
b10010010 5

#1550000
0!
0.
b10010010 :

#1555000
1!
1.
b10010011 5

#1560000
0!
0.
b10010011 :

#1565000
1!
1.
b10010100 5

#1570000
0!
0.
b10010100 :

#1575000
1!
1.
b10010101 5

#1580000
0!
0.
b10010101 :

#1585000
1!
1.
b10010110 5

#1590000
0!
0.
b10010110 :

#1595000
1!
1.
b10010111 5

#1600000
0!
0.
b10010111 :

#1605000
1!
1.
b10011000 5

#1610000
0!
0.
b10011000 :

#1615000
1!
1.
b10011001 5

#1620000
0!
0.
b10011001 :

#1625000
1!
1.
b10011010 5

#1630000
0!
0.
b10011010 :

#1635000
1!
1.
b10011011 5

#1640000
0!
0.
b10011011 :

#1645000
1!
1.
b10011100 5

#1650000
0!
0.
b10011100 :

#1655000
1!
1.
b10011101 5

#1660000
0!
0.
b10011101 :

#1665000
1!
1.
b10011110 5

#1670000
0!
0.
b10011110 :

#1675000
1!
1.
b10011111 5

#1680000
0!
0.
b10011111 :

#1685000
1!
1.
b10100000 5

#1690000
0!
0.
b10100000 :

#1695000
1!
1.
b10100001 5

#1700000
0!
0.
b10100001 :

#1705000
1!
1.
b10100010 5

#1710000
0!
0.
b10100010 :

#1715000
1!
1.
b10100011 5

#1720000
0!
0.
b10100011 :

#1725000
1!
1.
b10100100 5

#1730000
0!
0.
b10100100 :

#1735000
1!
1.
b10100101 5

#1740000
0!
0.
b10100101 :

#1745000
1!
1.
b10100110 5

#1750000
0!
0.
b10100110 :

#1755000
1!
1.
b10100111 5

#1760000
0!
0.
b10100111 :

#1765000
1!
1.
b10101000 5

#1770000
0!
0.
b10101000 :

#1775000
1!
1.
b10101001 5

#1780000
0!
0.
b10101001 :

#1785000
1!
1.
b10101010 5

#1790000
0!
0.
b10101010 :

#1795000
1!
1.
b10101011 5

#1800000
0!
0.
b10101011 :

#1805000
1!
1.
b10101100 5

#1810000
0!
0.
b10101100 :

#1815000
1!
1.
b10101101 5

#1820000
0!
0.
b10101101 :

#1825000
1!
1.
b10101110 5

#1830000
0!
0.
b10101110 :

#1835000
1!
1.
b10101111 5

#1840000
0!
0.
b10101111 :

#1845000
1!
1.
b10110000 5

#1850000
0!
0.
b10110000 :

#1855000
1!
1.
b10110001 5

#1860000
0!
0.
b10110001 :

#1865000
1!
1.
b10110010 5

#1870000
0!
0.
b10110010 :

#1875000
1!
1.
b10110011 5

#1880000
0!
0.
b10110011 :

#1885000
1!
1.
b10110100 5

#1890000
0!
0.
b10110100 :

#1895000
1!
1.
b10110101 5

#1900000
0!
0.
b10110101 :

#1905000
1!
1.
b10110110 5

#1910000
0!
0.
b10110110 :

#1915000
1!
1.
b10110111 5

#1920000
0!
0.
b10110111 :

#1925000
1!
1.
b10111000 5

#1930000
0!
0.
b10111000 :

#1935000
1!
1.
b10111001 5

#1940000
0!
0.
b10111001 :

#1945000
1!
1.
b10111010 5

#1950000
0!
0.
b10111010 :

#1955000
1!
1.
b10111011 5

#1960000
0!
0.
b10111011 :

#1965000
1!
1.
b10111100 5

#1970000
0!
0.
b10111100 :

#1975000
1!
1.
b10111101 5

#1980000
0!
0.
b10111101 :

#1985000
1!
1.
b10111110 5

#1990000
0!
0.
b10111110 :

#1995000
1!
1.
b10111111 5

#2000000
0!
0.
b10111111 :

#2005000
1!
1.
b11000000 5

#2010000
0!
0.
b11000000 :

#2015000
1!
1.
b11000001 5

#2020000
0!
0.
b11000001 :

#2025000
1!
1.
b11000010 5

#2030000
0!
0.
b11000010 :

#2035000
1!
1.
b11000011 5

#2040000
0!
0.
b11000011 :

#2045000
1!
1.
b11000100 5

#2050000
0!
0.
b11000100 :

#2055000
1!
1.
b11000101 5

#2060000
0!
0.
b11000101 :

#2065000
1!
1.
b11000110 5

#2070000
0!
0.
b11000110 :

#2075000
1!
1.
b11000111 5

#2080000
0!
0.
b11000111 :

#2085000
1!
1.
b11001000 5

#2090000
0!
0.
b11001000 :

#2095000
1!
1.
b11001001 5

#2100000
0!
0.
b11001001 :

#2105000
1!
1.
b11001010 5

#2110000
0!
0.
b11001010 :

#2115000
1!
1.
b11001011 5

#2120000
0!
0.
b11001011 :

#2125000
1!
1.
b11001100 5

#2130000
0!
0.
b11001100 :

#2135000
1!
1.
b11001101 5

#2140000
0!
0.
b11001101 :

#2145000
1!
1.
b11001110 5

#2150000
0!
0.
b11001110 :

#2155000
1!
1.
b11001111 5

#2160000
0!
0.
b11001111 :

#2165000
1!
1.
b11010000 5

#2170000
0!
0.
b11010000 :

#2175000
1!
1.
b11010001 5

#2180000
0!
0.
b11010001 :

#2185000
1!
1.
b11010010 5

#2190000
0!
0.
b11010010 :

#2195000
1!
1.
b11010011 5

#2200000
0!
0.
b11010011 :

#2205000
1!
1.
b11010100 5

#2210000
0!
0.
b11010100 :

#2215000
1!
1.
b11010101 5

#2220000
0!
0.
b11010101 :

#2225000
1!
1.
b11010110 5

#2230000
0!
0.
b11010110 :

#2235000
1!
1.
b11010111 5

#2240000
0!
0.
b11010111 :

#2245000
1!
1.
b11011000 5

#2250000
0!
0.
b11011000 :

#2255000
1!
1.
b11011001 5

#2260000
0!
0.
b11011001 :

#2265000
1!
1.
b11011010 5

#2270000
0!
0.
b11011010 :

#2275000
1!
1.
b11011011 5

#2280000
0!
0.
b11011011 :

#2285000
1!
1.
b11011100 5

#2290000
0!
0.
b11011100 :

#2295000
1!
1.
b11011101 5

#2300000
0!
0.
b11011101 :

#2305000
1!
1.
b11011110 5

#2310000
0!
0.
b11011110 :

#2315000
1!
1.
b11011111 5

#2320000
0!
0.
b11011111 :

#2325000
1!
1.
b11100000 5

#2330000
0!
0.
b11100000 :

#2335000
1!
1.
b11100001 5

#2340000
0!
0.
b11100001 :

#2345000
1!
1.
b11100010 5

#2350000
0!
0.
b11100010 :

#2355000
1!
1.
b11100011 5

#2360000
0!
0.
b11100011 :

#2365000
1!
1.
b11100100 5

#2370000
0!
0.
b11100100 :

#2375000
1!
1.
b11100101 5

#2380000
0!
0.
b11100101 :

#2385000
1!
1.
b11100110 5

#2390000
0!
0.
b11100110 :

#2395000
1!
1.
b11100111 5

#2400000
0!
0.
b11100111 :

#2405000
1!
1.
b11101000 5

#2410000
0!
0.
b11101000 :

#2415000
1!
1.
b11101001 5

#2420000
0!
0.
b11101001 :

#2425000
1!
1.
b11101010 5

#2430000
0!
0.
b11101010 :

#2435000
1!
1.
b11101011 5

#2440000
0!
0.
b11101011 :

#2445000
1!
1.
b11101100 5

#2450000
0!
0.
b11101100 :

#2455000
1!
1.
b11101101 5

#2460000
0!
0.
b11101101 :

#2465000
1!
1.
b11101110 5

#2470000
0!
0.
b11101110 :

#2475000
1!
1.
b11101111 5

#2480000
0!
0.
b11101111 :

#2485000
1!
1.
b11110000 5

#2490000
0!
0.
b11110000 :

#2495000
1!
1.
b11110001 5

#2500000
0!
0.
b11110001 :

#2505000
1!
1.
b11110010 5

#2510000
0!
0.
b11110010 :

#2515000
1!
1.
b11110011 5

#2520000
0!
0.
b11110011 :

#2525000
1!
1.
b11110100 5

#2530000
0!
0.
b11110100 :

#2535000
1!
1.
b11110101 5

#2540000
0!
0.
b11110101 :

#2545000
1!
1.
b11110110 5

#2550000
0!
0.
b11110110 :

#2555000
1!
1.
b11110111 5

#2560000
0!
0.
b11110111 :

#2565000
1!
1.
b11111000 5

#2570000
0!
0.
b11111000 :

#2575000
1!
1.
b11111001 5

#2580000
0!
0.
b11111001 :

#2585000
1!
1.
b11111010 5

#2590000
0!
0.
b11111010 :

#2595000
1!
1.
b11111011 5

#2600000
0!
0.
b11111011 :

#2605000
1!
1.
b11111100 5

#2610000
0!
0.
b11111100 :

#2615000
1!
1.
b11111101 5

#2620000
0!
0.
b11111101 :

#2625000
1!
1.
b11111110 5

#2630000
0!
0.
b11111110 :

#2635000
1!
1.
b11111111 5

#2640000
0!
0.
b11111111 :

#2645000
1!
1.
b100000000 5

#2650000
0!
0.
b100000000 :

#2655000
1!
1.
b100000001 5

#2660000
0!
0.
b100000001 :

#2665000
1!
1.
b100000010 5

#2670000
0!
0.
b100000010 :

#2675000
1!
1.
b100000011 5

#2680000
0!
0.
b100000011 :

#2685000
1!
1.
b100000100 5

#2690000
0!
0.
b100000100 :

#2695000
1!
1.
b100000101 5

#2700000
0!
0.
b100000101 :

#2705000
1!
1.
b100000110 5

#2710000
0!
0.
b100000110 :

#2715000
1!
1.
b100000111 5

#2720000
0!
0.
b100000111 :

#2725000
1!
1.
b100001000 5

#2730000
0!
0.
b100001000 :

#2735000
1!
1.
b100001001 5

#2740000
0!
0.
b100001001 :

#2745000
1!
1.
b100001010 5

#2750000
0!
0.
b100001010 :

#2755000
1!
1.
b100001011 5

#2760000
0!
0.
b100001011 :

#2765000
1!
1.
b100001100 5

#2770000
0!
0.
b100001100 :

#2775000
1!
1.
b100001101 5

#2780000
0!
0.
b100001101 :

#2785000
1!
1.
b100001110 5

#2790000
0!
0.
b100001110 :

#2795000
1!
1.
b100001111 5

#2800000
0!
0.
b100001111 :

#2805000
1!
1.
b100010000 5

#2810000
0!
0.
b100010000 :

#2815000
1!
1.
b100010001 5

#2820000
0!
0.
b100010001 :

#2825000
1!
1.
b100010010 5

#2830000
0!
0.
b100010010 :

#2835000
1!
1.
b100010011 5

#2840000
0!
0.
b100010011 :

#2845000
1!
1.
b100010100 5

#2850000
0!
0.
b100010100 :

#2855000
1!
1.
b100010101 5

#2860000
0!
0.
b100010101 :

#2865000
1!
1.
b100010110 5

#2870000
0!
0.
b100010110 :

#2875000
1!
1.
b100010111 5

#2880000
0!
0.
b100010111 :

#2885000
1!
1.
b100011000 5

